[
    {
        "question": "What is it called when a hockey team has more players on the ice than its opponent?",
        "answers": [
            "Power play",
            "Exotic blitz scheme",
            "Strong style"
        ],
        "questionNumber": 1,
        "time": 1534558010.4504201
    },
    {
        "question": "In which of these events do athletes have to clear a bar?",
        "answers": [
            "Long jump",
            "Pole vault",
            "Triple jump"
        ],
        "questionNumber": 2,
        "time": 1534558059.5992188
    },
    {
        "question": "What popular martial arts style is practiced by MMA fighters like Fabricio Werdum?",
        "answers": [
            "Brazilian jiu-jitsu",
            "Swedish karate",
            "Australian judo"
        ],
        "questionNumber": 3,
        "time": 1534558163.7483473
    },
    {
        "question": "What player just became the youngest since 1908 to homer in five straight MLB games?",
        "answers": [
            "Ronald Acuna Jr.",
            "Albert Pujols",
            "Ichiro"
        ],
        "questionNumber": 4,
        "time": 1534558213.8598466
    },
    {
        "question": "What sport did Randy Poffo play professionally before becoming \"The Macho Man\"?",
        "answers": [
            "Hockey",
            "Football",
            "Baseball"
        ],
        "questionNumber": 5,
        "time": 1534558286.8167129
    },
    {
        "question": "Who was the first woman to dunk in an official WNBA game?",
        "answers": [
            "Candace Parker",
            "Lisa Leslie",
            "Brittney Griner"
        ],
        "questionNumber": 6,
        "time": 1534558352.4674659
    },
    {
        "question": "Which of these MLB franchises does NOT currently feature its team name on standard home jerseys?",
        "answers": [
            "Angels",
            "Nationals",
            "Brewers"
        ],
        "questionNumber": 7,
        "time": 1534558417.9308076
    },
    {
        "question": "Which of these NFL rookie QBs threw the most interceptions in college?",
        "answers": [
            "Baker Mayfield",
            "Josh Rosen",
            "Sam Darnold"
        ],
        "questionNumber": 8,
        "time": 1534558473.1590858
    },
    {
        "question": "Which of these Team USA hockey stars scored the greatest number of goals in a single NHL season?",
        "answers": [
            "Brett Hull",
            "Patrick Kane",
            "Mike Modano"
        ],
        "questionNumber": 9,
        "time": 1534558534.6285083
    },
    {
        "question": "Which of these players has won the most MLB batting titles?",
        "answers": [
            "Miguel Cabrera",
            "Barry Bonds",
            "Pete Rose"
        ],
        "questionNumber": 10,
        "time": 1534558602.2861402
    },
    {
        "question": "Which of these racers is NOT tied for the record number of NASCAR Cup Series championships?",
        "answers": [
            "Jeff Gordon",
            "Jimmie Johnson",
            "Dale Earnhardt"
        ],
        "questionNumber": 11,
        "time": 1534558667.7492275
    },
    {
        "question": "Who is the only man to lead a US Olympic basketball team in scoring in two different Olympics?",
        "answers": [
            "Carmelo Anthony",
            "Kevin Durant",
            "Michael Jordan"
        ],
        "questionNumber": 12,
        "time": 1534558762.2628293,
        "answer": 2
    }
]